spider_kel/Tookit.py
spider_kel/__init__.py
spider_kel/spilt_func.py
zut_spider-0.1.3.dist-info/METADATA
zut_spider-0.1.3.dist-info/WHEEL
zut_spider-0.1.3.dist-info/top_level.txt
zut_spider-0.1.3.dist-info/RECORD
