Metadata-Version: 2.4
Name: zut-spider
Version: 0.1.3
Summary: spider for Ayn
Requires-Python: >=3.8
Requires-Dist: bs4
Requires-Dist: requests
